Metadata-Version: 2.1
Name: gydo.py
Version: 0.0.4
Summary: A Package for interacting with Discord's API
Home-page: UNKNOWN
Author: loldonut (John Heinrich)
License: Apache-2.0
Keywords: python,discord,gydo.py,discord api
Platform: UNKNOWN
License-File: LICENSE
